streelib/__init__.py
streelib/algths.py
streelib/halperfuncs.py
streelib/structures.py
the_simple_tree_lib-2.1.dist-info/DESCRIPTION.rst
the_simple_tree_lib-2.1.dist-info/METADATA
the_simple_tree_lib-2.1.dist-info/RECORD
the_simple_tree_lib-2.1.dist-info/WHEEL
the_simple_tree_lib-2.1.dist-info/entry_points.txt
the_simple_tree_lib-2.1.dist-info/metadata.json
the_simple_tree_lib-2.1.dist-info/top_level.txt
