Metadata-Version: 2.0
Name: the-simple-tree-lib
Version: 2.1
Summary: test work for job assigment. Tree alg.
Home-page: https://github.com/stivsh/ddtest_assigment
Author: Sorokin Stepan
Author-email: stivsh@gmail.com
License: NO
Platform: UNKNOWN
Requires-Dist: docopt
